huehue/__init__.py
huehue/bridge/__init__.py
huehue/bridge/discover.py
huehue/cli.py
huehue/config.py
huehue/huehue.py
huehue/models/__init__.py
huehue/utils.py
huehue-0.1.0.dist-info/entry_points.txt
huehue-0.1.0.dist-info/LICENSE
huehue-0.1.0.dist-info/WHEEL
huehue-0.1.0.dist-info/METADATA
huehue-0.1.0.dist-info/RECORD
