Metadata-Version: 2.1
Name: huehue
Version: 0.1.0
Summary: 
Author: Jay Looney
Author-email: jay.m.looney@gmail.com
Requires-Python: >=3.8,<4.0
Classifier: Programming Language :: Python :: 3
Classifier: Programming Language :: Python :: 3.8
Requires-Dist: click (>=7.1.2,<8.0.0)
Requires-Dist: click-log (>=0.3.2,<0.4.0)
Requires-Dist: python-decouple (>=3.3,<4.0)
Requires-Dist: urllib3 (>=1.25.9,<2.0.0)
